{"title":"Browserify all the things","headings":[],"date":"2014-01-30T00:00:00.000Z","lang":"fr","conference":"Toulouse JS #4","slides":"https://speakerdeck.com/moox/browserify-all-the-things","slidesEmbed":"https://speakerdeck.com/player/17613199ff744762be6b91074a7fe956?title=false","body":{"tag":"ul","children":["\n",{"tag":"li","children":[{"tag":"a","props":{"href":"https://twitter.com/davidwalshblog/statuses/428646150028009472"},"children":["https://twitter.com/davidwalshblog/statuses/428646150028009472"]}]},"\n",{"tag":"li","children":[{"tag":"a","props":{"href":"https://github.com/MoOx/jQuery.Loading-Indicator/"},"children":["https://github.com/MoOx/jQuery.Loading-Indicator/"]}]},"\n",{"tag":"li","children":[{"tag":"a","props":{"href":"https://github.com/MoOx/jQuery.External-Links/"},"children":["https://github.com/MoOx/jQuery.External-Links/"]}]},"\n",{"tag":"li","children":[{"tag":"a","props":{"href":"http://wiki.ecmascript.org/doku.php?id=harmony:modules"},"children":["http://wiki.ecmascript.org/doku.php?id=harmony:modules"]}]},"\n",{"tag":"li","children":[{"tag":"a","props":{"href":"https://github.com/substack/node-mkdirp"},"children":["https://github.com/substack/node-mkdirp"]}]},"\n",{"tag":"li","children":[{"tag":"a","props":{"href":"https://github.com/isaacs/rimraf"},"children":["https://github.com/isaacs/rimraf"]}]},"\n",{"tag":"li","children":[{"tag":"a","props":{"href":"http://requirejs.org/docs/release/2.1.10/minified/require.js"},"children":["http://requirejs.org/docs/release/2.1.10/minified/require.js"]}]},"\n",{"tag":"li","children":[{"tag":"a","props":{"href":"https://github.com/MoOx/dateranger/blob/master/index.js"},"children":["https://github.com/MoOx/dateranger/blob/master/index.js"]}]},"\n",{"tag":"li","children":[{"tag":"a","props":{"href":"http://putaindecode.fr/posts/js/browserify-all-the-things/"},"children":["http://putaindecode.fr/posts/js/browserify-all-the-things/"]}]},"\n"]}}